{"AllCards":[{"$type":"UnitCardData, Assembly-CSharp","Damage":1,"Health":2,"CardId":0,"CardSpritePath":"Basic Card","Abilities":[],"EnemyCard":false},{"$type":"UnitCardData, Assembly-CSharp","Damage":5,"Health":5,"CardId":1,"CardSpritePath":"Basic Card","Abilities":[{"AbilityType":2,"LightModifier":2,"DarkModifier":2}],"EnemyCard":false},{"$type":"UnitCardData, Assembly-CSharp","Damage":1,"Health":1,"CardId":2,"CardSpritePath":"Basic Card","Abilities":[{"AbilityType":1,"LightModifier":2,"DarkModifier":2},{"AbilityType":3,"LightModifier":6,"DarkModifier":6}],"EnemyCard":false},{"CardId":3,"CardSpritePath":"Basic Card","Abilities":[{"AbilityType":3,"LightModifier":2,"DarkModifier":2}],"EnemyCard":false},{"CardId":4,"CardSpritePath":"Basic Card","Abilities":[{"AbilityType":5,"LightModifier":3,"DarkModifier":5}],"EnemyCard":false},{"CardId":5,"CardSpritePath":"Basic Card","Abilities":[{"AbilityType":6,"LightModifier":1,"DarkModifier":1}],"EnemyCard":false},{"$type":"UnitCardData, Assembly-CSharp","Damage":2,"Health":5,"CardId":6,"CardSpritePath":"Basic Card","Abilities":[],"EnemyCard":true},{"$type":"UnitCardData, Assembly-CSharp","Damage":3,"Health":3,"CardId":7,"CardSpritePath":"Basic Card","Abilities":[],"EnemyCard":true},{"$type":"UnitCardData, Assembly-CSharp","Damage":5,"Health":2,"CardId":8,"CardSpritePath":"Basic Card","Abilities":[],"EnemyCard":true}],"AllAbilities":[{"AbilityType":1,"ActivationTime":2,"LightSideData":{"AbilityName":"ThornyRoses","AbilityDesc":"Heal King for @ when attacked","AbilitySpritePath":"plain light ability"},"DarkSideData":{"AbilityName":"ThornyRoses","AbilityDesc":"Deal damage equal @ when attacked","AbilitySpritePath":"plain dark ability"}},{"AbilityType":2,"ActivationTime":1,"LightSideData":{"AbilityName":"BloodPact","AbilityDesc":"Instead of attacking unit will heal @ amount and lose 1-1","AbilitySpritePath":"plain light ability"},"DarkSideData":{"AbilityName":"Blood Pact","AbilityDesc":"If attack does not hit a unit, King loses @ health","AbilitySpritePath":"plain dark ability"}},{"AbilityType":3,"ActivationTime":0,"LightSideData":{"AbilityName":"Health Gain","AbilityDesc":"Gain @ health on summon","AbilitySpritePath":"plain light ability"},"DarkSideData":{"AbilityName":"Health Gain","AbilityDesc":"Gain @ health on summon","AbilitySpritePath":"plain dark ability"}},{"AbilityType":4,"ActivationTime":0,"LightSideData":{"AbilityName":"Damage","AbilityDesc":"Deal @ Damage","AbilitySpritePath":"plain light ability"},"DarkSideData":{"AbilityName":"Heal","AbilityDesc":"Heal @ Damage","AbilitySpritePath":"plain dark ability"}},{"AbilityType":5,"ActivationTime":0,"LightSideData":{"AbilityName":"Enemies to Lovers","AbilityDesc":"Choose an ally and an enemy to gain @ health","AbilitySpritePath":"plain light ability"},"DarkSideData":{"AbilityName":"Eye for an Eye","AbilityDesc":"Choose and enemy and an ally to take @ damage.","AbilitySpritePath":"plain dark ability"}},{"AbilityType":6,"ActivationTime":0,"LightSideData":{"AbilityName":"Damage Resistance","AbilityDesc":"Affected unit takes half damage for @ turns.","AbilitySpritePath":"plain light ability"},"DarkSideData":{"AbilityName":"Sensitive Skin","AbilityDesc":"Affected unit takes double damage for @ turns.","AbilitySpritePath":"plain dark ability"}}]}